{
  "鯊魚級": {
    "船體": {
      "鈷鐵錠": 36,
      "綠金錠": 18,
      "玫瑰金錠": 21,
      "秘銀板": 18,
      "黑鐵鉚釘": 18,
      "秘銀鉚釘": 18,
      "雪松木材": 9,
      "胡桃木材": 18,
      "雲杉木材": 18,
      "鬼膠": 18,
      "清漆": 18,
      "黑鐵釘": 18
    },
    "船尾": {
      "白鋼錠": 54,
      "鈷鐵錠": 78,
      "玄鋼錠": 9,
      "白銀錠": 30,
      "白鋼鉚釘": 24,
      "秘銀鉚釘": 30,
      "白鋼連接板": 30,
      "鈷鐵連接板": 24,
      "古神木材": 9
    },
    "船首": {
      "白鋼錠": 30,
      "鈷鐵錠": 18,
      "玄鋼錠": 12,
      "白銀錠": 30,
      "白鋼鉚釘": 60,
      "秘銀鉚釘": 30,
      "白鋼連接板": 30,
      "鈷鐵連接板": 30,
      "古神木材": 9
    },
    "艦橋": {
      "白鋼錠": 21,
      "鈷鐵錠": 18,
      "玄鋼錠": 24,
      "玄鋼塊": 21,
      "綠金錠": 21,
      "黑鐵鉚釘": 21,
      "白鋼鉚釘": 42,
      "鈷鐵鉚釘": 21,
      "硬化雲杉木材": 12,
      "黑鐵釘": 21
    }
  },
  "甲鱟級": {
    "船體": {
      "鈷鐵錠": 24,
      "綠金錠": 24,
      "白鋼板": 24,
      "黑鐵鉚釘": 24,
      "鈷鐵鉚釘": 24,
      "聖蜥蜴革": 24,
      "橡木木材": 24,
      "雲杉木材": 24,
      "黑膠": 9,
      "清漆": 18,
      "白鋼釘": 24,
      "古神木材": 24,
      "致遠帆布": 9,
      "加隆德鋼": 9
    },
    "船尾": {
      "白鋼錠": 24,
      "鈷鐵錠": 24,
      "玄鋼錠": 9,
      "秘銀錠": 30,
      "玄鋼板": 18,
      "白鋼鉚釘": 24,
      "秘銀鉚釘": 60,
      "玻璃板": 30,
      "鈷鐵連接板": 30,
      "鎢鋼錠": 18,
      "靈銀錠": 18,
      "加隆德鋼": 9
    },
    "船首": {
      "白鋼錠": 30,
      "玄鋼錠": 9,
      "秘銀錠": 30,
      "玫瑰金錠": 18,
      "玄鋼板": 9,
      "白鋼鉚釘": 30,
      "鈷鐵鉚釘": 30,
      "秘銀鉚釘": 30,
      "玻璃板": 30,
      "白鋼連接板": 30,
      "鈷鐵連接板": 30,
      "靈銀錠": 18,
      "加隆德鋼": 9
    },
    "艦橋": {
      "白鋼錠": 21,
      "鈷鐵錠": 21,
      "玄鋼錠": 18,
      "白鋼鉚釘": 42,
      "玄鋼鉚釘": 21,
      "秘銀鉚釘": 18,
      "硬化雲杉木材": 12,
      "白鋼釘": 21,
      "致遠帆布": 9,
      "飛龍革": 18,
      "加隆德鋼": 9
    }
  },
  "鬚鯨級": {
    "船體": {
      "玫瑰金錠": 24,
      "鈷鐵板": 24,
      "鈷鐵鉚釘": 54,
      "胡桃木材": 24,
      "雲杉木材": 24,
      "黑膠": 12,
      "清漆": 30,
      "黑鐵釘": 24,
      "靈銀錠": 18,
      "聖雪松材": 12,
      "蒼天石": 9,
      "加隆德鋼": 9
    },
    "船尾": {
      "白鋼錠": 30,
      "玄鋼錠": 30,
      "玄鋼塊": 30,
      "白鋼鉚釘": 30,
      "鈷鐵鉚釘": 30,
      "玄鋼鉚釘": 12,
      "秘銀鉚釘": 30,
      "白鋼釘": 30,
      "古神木材": 12,
      "靈銀錠": 12,
      "蒼天石": 9,
      "加隆德鋼": 9
    },
    "船首": {
      "白鋼錠": 30,
      "玄鋼錠": 12,
      "玫瑰金錠": 12,
      "白鋼鉚釘": 60,
      "玄鋼鉚釘": 30,
      "鈷鐵連接板": 60,
      "靈銀錠": 18,
      "聖雪松材": 12,
      "蒼天石": 9,
      "加隆德鋼": 9
    },
    "艦橋": {
      "白鋼錠": 30,
      "玄鋼錠": 30,
      "玫瑰金錠": 12,
      "白鋼鉚釘": 60,
      "鈷鐵鉚釘": 18,
      "鈷鐵連接板": 60,
      "靈銀錠": 18,
      "聖雪松材": 12,
      "蒼天石": 9,
      "加隆德鋼": 9
    }
  },
  "腔棘魚級": {
    "船體": {
      "鈷鐵板": 18,
      "鈷鐵鉚釘": 30,
      "玄鋼鉚釘": 30,
      "黑膠": 12,
      "鈷鐵連接板": 30,
      "靈銀錠": 48,
      "硬銀塊": 18,
      "皇金塊": 18,
      "白鈦錠": 30,
      "暗栗木木材": 30,
      "加隆德鋼": 9
    },
    "船尾": {
      "黃金錠": 15,
      "鈷鐵鉚釘": 30,
      "玄鋼鉚釘": 60,
      "鈷鐵連接板": 30,
      "靈銀錠": 48,
      "硬銀塊": 30,
      "皇金塊": 30,
      "白鈦錠": 30,
      "蒼天石": 9
    },
    "船首": {
      "玄鋼錠": 18,
      "玫瑰金錠": 18,
      "鈷鐵板": 30,
      "鈷鐵鉚釘": 30,
      "玄鋼鉚釘": 60,
      "鈷鐵連接板": 60,
      "鐵刀木木材": 9,
      "靈銀錠": 18,
      "白鈦錠": 30
    },
    "艦橋": {
      "玫瑰金塊": 30,
      "鈷鐵板": 18,
      "鈷鐵鉚釘": 30,
      "玄鋼鉚釘": 36,
      "黃玉": 6,
      "鈷鐵連接板": 30,
      "白金塊": 12,
      "鐵刀木木材": 9,
      "靈銀錠": 48,
      "白鈦錠": 30,
      "水淙石": 12
    }
  },
  "希爾德拉級": {
    "船體": {
      "玄鋼板": 9,
      "玄鋼鉚釘": 15,
      "黑膠": 12,
      "靈銀錠": 30,
      "硬銀塊": 18,
      "皇金塊": 18,
      "精金鉚釘": 15,
      "暗栗木木材": 30,
      "樺木木材": 21,
      "鐵刀木角材": 6,
      "超硬加隆德鋼": 6,
      "鐵紋鋼": 9
    },
    "船尾": {
      "玄鋼塊": 30,
      "鈷鐵鉚釘": 21,
      "玄鋼鉚釘": 15,
      "鎢鋼錠": 9,
      "靈銀錠": 30,
      "硬銀塊": 18,
      "皇金塊": 15,
      "白鈦錠": 30,
      "精金塊": 15,
      "樺木木材": 30,
      "鐵刀木角材": 6,
      "鐵紋鋼": 9
    },
    "船首": {
      "玄鋼錠": 15,
      "玄鋼板": 9,
      "玄鋼鉚釘": 30,
      "鈷鐵連接板": 30,
      "靈銀錠": 60,
      "硬銀塊": 18,
      "皇金塊": 15,
      "精金塊": 15,
      "精金鉚釘": 15,
      "鐵紋鋼": 9
    },
    "艦橋": {
      "黃金錠": 15,
      "玄鋼板": 9,
      "鈷鐵鉚釘": 30,
      "玄鋼鉚釘": 15,
      "靈銀錠": 30,
      "皇金塊": 60,
      "白鈦錠": 30,
      "精金鉚釘": 15,
      "樺木木材": 15,
      "鐵刀木角材": 6,
      "鐵紋鋼": 9
    }
  },
  "鯊魚改級": {
    "船體": {
      "玫瑰金錠": 24,
      "秘銀板": 18,
      "白鋼鉚釘": 24,
      "黑膠": 18,
      "清漆": 30,
      "白金錠": 24,
      "硬銀附魔墨水": 18,
      "超硬加隆德鋼": 9,
      "薔薇輝石": 15,
      "鯊魚級船體骨架": 1,
      "柳杉木材": 9,
      "純鈦板": 9
    },
    "船尾": {
      "白鋼連接板": 30,
      "鎢鋼錠": 9,
      "硬銀錠": 30,
      "白鈦錠": 60,
      "硬銀附魔墨水": 18,
      "超硬加隆德鋼": 9,
      "薔薇輝石": 12,
      "鯊魚級船尾骨架": 1,
      "柳杉木材": 9,
      "純鈦板": 9
    },
    "船首": {
      "白鋼連接板": 30,
      "鎢鋼錠": 12,
      "硬銀錠": 30,
      "硬銀附魔墨水": 18,
      "超硬加隆德鋼": 9,
      "薔薇輝石": 12,
      "鯊魚級船首骨架": 1,
      "柳杉木材": 9,
      "純鈦板": 9
    },
    "艦橋": {
      "鈷鐵錠": 21,
      "玫瑰金錠": 21,
      "玄鋼鉚釘": 21,
      "鎢鋼錠": 24,
      "硬銀附魔墨水": 18,
      "超硬加隆德鋼": 9,
      "薔薇輝石": 6,
      "鯊魚級艦橋骨架": 1,
      "柳杉木材": 9,
      "純鈦板": 9
    }
  },
  "甲鱟改級": {
    "船體": {
      "玫瑰金錠": 24,
      "鈷鐵板": 24,
      "白鋼鉚釘": 24,
      "玄鋼鉚釘": 24,
      "翼膠": 12,
      "致遠帆布": 9,
      "硬銀附魔墨水": 18,
      "超硬加隆德鋼": 9,
      "薔薇輝石": 15,
      "迦迦納怪鳥革": 24,
      "甲鱟級船體骨架": 1,
      "柳杉木材": 9,
      "純鈦板": 9
    },
    "船尾": {
      "黃金錠": 30,
      "鈷鐵連接板": 30,
      "鎢鋼錠": 9,
      "皇金錠": 18,
      "硬銀附魔墨水": 18,
      "光銀錠": 12,
      "超硬加隆德鋼": 9,
      "強化玻璃板": 30,
      "薔薇輝石": 12,
      "甲鱟級船尾骨架": 1,
      "柳杉木材": 9,
      "純鈦板": 9
    },
    "船首": {
      "黃金錠": 30,
      "白鋼連接板": 30,
      "鎢鋼錠": 12,
      "白金錠": 18,
      "硬銀附魔墨水": 18,
      "光銀錠": 18,
      "超硬加隆德鋼": 9,
      "強化玻璃板": 30,
      "薔薇輝石": 12,
      "甲鱟級船首骨架": 1,
      "柳杉木材": 9,
      "純鈦板": 9
    },
    "艦橋": {
      "秘銀鉚釘": 21,
      "致遠帆布": 9,
      "白鈦錠": 21,
      "靈銀鉚釘": 18,
      "巨龍革": 18,
      "硬銀附魔墨水": 18,
      "超硬加隆德鋼": 9,
      "薔薇輝石": 6,
      "甲鱟級艦橋骨架": 1,
      "柳杉木材": 9,
      "純鈦板": 9
    }
  },
  "鬚鯨改級": {
    "船體": {
      "玄鋼鉚釘": 24,
      "翼膠": 12,
      "清漆": 30,
      "白金錠": 24,
      "硬銀附魔墨水": 18,
      "光銀錠": 18,
      "超硬加隆德鋼": 9,
      "山毛櫸木材": 12,
      "薔薇輝石": 15,
      "鬚鯨級船體骨架": 1,
      "柳杉木材": 9,
      "純鈦板": 9
    },
    "船尾": {
      "鈷鐵錠": 30,
      "秘銀鉚釘": 30,
      "鎢鋼錠": 9,
      "靈銀鉚釘": 15,
      "硬銀附魔墨水": 18,
      "光銀錠": 12,
      "超硬加隆德鋼": 9,
      "薔薇輝石": 12,
      "鬚鯨級船尾骨架": 1,
      "柳杉木材": 9,
      "純鈦板": 9
    },
    "船首": {
      "鈷鐵連接板": 30,
      "鎢鋼錠": 12,
      "白金錠": 18,
      "靈銀鉚釘": 30,
      "硬銀附魔墨水": 18,
      "光銀錠": 18,
      "超硬加隆德鋼": 9,
      "薔薇輝石": 12,
      "鬚鯨級船首骨架": 0,
      "柳杉木材": 9,
      "純鈦板": 9
    },
    "艦橋": {
      "玄鋼鉚釘": 21,
      "鈷鐵連接板": 30,
      "鎢鋼錠": 24,
      "白金錠": 12,
      "硬銀附魔墨水": 18,
      "光銀錠": 18,
      "超硬加隆德鋼": 9,
      "薔薇輝石": 6,
      "鬚鯨級艦橋骨架": 1,
      "柳杉木材": 9,
      "純鈦板": 9
    }
  },
  "腔棘魚改級": {
    "船體": {
      "翼膠": 12,
      "皇金塊": 18,
      "靈銀鉚釘": 30,
      "硬銀附魔墨水": 18,
      "光銀錠": 18,
      "超硬加隆德鋼": 9,
      "白銅塊": 18,
      "薔薇輝石": 15,
      "腔棘魚級船體骨架": 1,
      "柳杉木材": 9,
      "純鈦板": 9
    },
    "船尾": {
      "皇金塊": 30,
      "硬銀附魔墨水": 18,
      "光銀錠": 12,
      "荒神鋼錠": 15,
      "超硬加隆德鋼": 9,
      "白銅塊": 18,
      "鉬鋼錠": 30,
      "薔薇輝石": 12,
      "腔棘魚級船尾骨架": 1,
      "柳杉木材": 9,
      "純鈦板": 9
    },
    "船首": {
      "鎢鋼錠": 12,
      "鐵刀木木材": 9,
      "靈銀鉚釘": 60,
      "硬銀附魔墨水": 18,
      "超硬加隆德鋼": 9,
      "鉬鋼錠": 30,
      "薔薇輝石": 12,
      "腔棘魚級船首骨架": 1,
      "柳杉木材": 9,
      "純鈦板": 9
    },
    "艦橋": {
      "鐵刀木木材": 9,
      "靈銀鉚釘": 36,
      "硬銀附魔墨水": 18,
      "光銀錠": 18,
      "超硬加隆德鋼": 9,
      "鉬鋼錠": 30,
      "鋰輝石": 6,
      "薔薇輝石": 6,
      "腔棘魚級艦橋骨架": 1,
      "柳杉木材": 9,
      "純鈦板": 9
    }
  },
  "希爾德拉改級": {
    "船體": {
      "翼膠": 12,
      "靈銀鉚釘": 30,
      "祝聖栗木木材": 30,
      "硬銀附魔墨水": 18,
      "鐵刀木角材": 6,
      "光銀錠": 18,
      "超硬加隆德鋼": 9,
      "薔薇輝石": 15,
      "希爾德拉級船體骨架": 1,
      "柳杉木材": 9,
      "純鈦板": 9
    },
    "船尾": {
      "皇金錠": 18,
      "精金塊": 15,
      "靈銀鉚釘": 15,
      "硬銀附魔墨水": 18,
      "鐵刀木角材": 6,
      "超硬加隆德鋼": 9,
      "白銅塊": 18,
      "薔薇輝石": 12,
      "希爾德拉級船尾骨架": 1,
      "柳杉木材": 9,
      "純鈦板": 9
    },
    "船首": {
      "鎢鋼錠": 12,
      "精金塊": 15,
      "精金鉚釘": 15,
      "硬銀附魔墨水": 18,
      "光銀錠": 18,
      "超硬加隆德鋼": 9,
      "白銅塊": 18,
      "薔薇輝石": 12,
      "希爾德拉級船首骨架": 1,
      "柳杉木材": 9,
      "純鈦板": 9
    },
    "艦橋": {
      "鎢鋼方板": 9,
      "靈銀鉚釘": 15,
      "精金鉚釘": 15,
      "硬銀附魔墨水": 18,
      "鐵刀木角材": 6,
      "超硬加隆德鋼": 9,
      "鉬鋼錠": 30,
      "薔薇輝石": 6,
      "希爾德拉級艦橋骨架": 1,
      "柳杉木材": 9,
      "純鈦板": 9
    }
  }
}